ess/__init__.py
ess/ess.py
indomart-1.0.0.dist-info/METADATA
indomart-1.0.0.dist-info/WHEEL
indomart-1.0.0.dist-info/entry_points.txt
indomart-1.0.0.dist-info/top_level.txt
indomart-1.0.0.dist-info/RECORD
