Metadata-Version: 2.1
Name: indomart
Version: 1.0.0
Summary: hanya sebuah script biasa
Home-page: https://github.com/username/my_project
Author: robbi 13
Author-email: email@example.com
